{
  "updatedAt": "2026-04-24T08:01:34.996Z",
  "matchesByDate": {
    "2026-04-24": [
      {
        "time": "21:00",
        "home": "Puebla",
        "away": "Querétaro",
        "channels": [
          "FOX One",
          "TV Azteca",
          "Azteca Deportes Network",
          "Tubi",
          "Azteca 7"
        ]
      }
    ],
    "2026-04-25": [
      {
        "time": "17:00",
        "home": "Pachuca",
        "away": "Pumas UNAM",
        "channels": [
          "FOX One"
        ]
      },
      {
        "time": "17:00",
        "home": "Tigres UANL",
        "away": "Mazatlán FC",
        "channels": [
          "FOX One",
          "TV Azteca",
          "Azteca Deportes Network",
          "Tubi",
          "Azteca 7"
        ]
      },
      {
        "time": "19:00",
        "home": "Toluca",
        "away": "Club León",
        "channels": [
          "TV Azteca",
          "FOX One",
          "Azteca Deportes Network",
          "Azteca 7"
        ]
      },
      {
        "time": "19:07",
        "home": "Chivas Guadalajara",
        "away": "Tijuana",
        "channels": [
          "Amazon Prime Video (Míralo en vivo)"
        ]
      },
      {
        "time": "21:00",
        "home": "América",
        "away": "Atlas",
        "channels": [
          "TUDN",
          "ViX Premium",
          "Layvtime YouTube",
          "Canal 5"
        ]
      },
      {
        "time": "21:00",
        "home": "FC Juárez",
        "away": "Atlético San Luis",
        "channels": [
          "FOX One",
          "TV Azteca",
          "Azteca Deportes Network",
          "Azteca 7"
        ]
      }
    ],
    "2026-04-26": [
      {
        "time": "17:00",
        "home": "Santos Laguna",
        "away": "Monterrey",
        "channels": [
          "TUDN",
          "ViX Premium",
          "Layvtime YouTube",
          "Disney+ Premium",
          "Canal 5",
          "ESPN 2"
        ]
      },
      {
        "time": "19:00",
        "home": "Cruz Azul",
        "away": "Necaxa",
        "channels": [
          "TUDN",
          "ViX Premium",
          "Layvtime YouTube",
          "Canal 5"
        ]
      }
    ]
  }
}